<?xml version="1.0" encoding="UTF-8"?>
<!DOCTYPE nmaprun>
<?xml-stylesheet href="file:///usr/bin/../share/nmap/nmap.xsl" type="text/xsl"?>
<!-- Nmap 7.40 scan initiated Sat Jun  3 17:29:00 2017 as: nmap -sU -&#45;top-ports 100 -oA udpConnect_10.11.1.0-254 10.11.1.0/24 -->
<nmaprun scanner="nmap" args="nmap -sU -&#45;top-ports 100 -oA udpConnect_10.11.1.0-254 10.11.1.0/24" start="1496525340" startstr="Sat Jun  3 17:29:00 2017" version="7.40" xmloutputversion="1.04">
<scaninfo type="udp" protocol="udp" numservices="100" services="7,9,17,19,49,53,67-69,80,88,111,120,123,135-139,158,161-162,177,427,443,445,497,500,514-515,518,520,593,623,626,631,996-999,1022-1023,1025-1030,1433-1434,1645-1646,1701,1718-1719,1812-1813,1900,2000,2048-2049,2222-2223,3283,3456,3703,4444,4500,5000,5060,5353,5632,9200,10000,17185,20031,30718,31337,32768-32769,32771,32815,33281,49152-49154,49156,49181-49182,49185-49186,49188,49190-49194,49200-49201,65024"/>
<verbose level="0"/>
<debugging level="0"/>
<host starttime="1496525340" endtime="1496525447"><status state="up" reason="arp-response" reason_ttl="0"/>
<address addr="10.11.1.5" addrtype="ipv4"/>
<address addr="00:50:56:89:28:DB" addrtype="mac" vendor="VMware"/>
<hostnames>
</hostnames>
<ports><extraports state="closed" count="93">
<extrareasons reason="port-unreaches" count="93"/>
</extraports>
<port protocol="udp" portid="135"><state state="open" reason="udp-response" reason_ttl="128"/><service name="msrpc" method="table" conf="3"/></port>
<port protocol="udp" portid="137"><state state="open" reason="udp-response" reason_ttl="128"/><service name="netbios-ns" method="table" conf="3"/></port>
<port protocol="udp" portid="138"><state state="open|filtered" reason="no-response" reason_ttl="0"/><service name="netbios-dgm" method="table" conf="3"/></port>
<port protocol="udp" portid="445"><state state="open|filtered" reason="no-response" reason_ttl="0"/><service name="microsoft-ds" method="table" conf="3"/></port>
<port protocol="udp" portid="1026"><state state="open|filtered" reason="no-response" reason_ttl="0"/><service name="win-rpc" method="table" conf="3"/></port>
<port protocol="udp" portid="1027"><state state="open|filtered" reason="no-response" reason_ttl="0"/><service name="unknown" method="table" conf="3"/></port>
<port protocol="udp" portid="1028"><state state="open|filtered" reason="no-response" reason_ttl="0"/><service name="ms-lsa" method="table" conf="3"/></port>
</ports>
<times srtt="30709" rttvar="1031" to="100000"/>
</host>
<host starttime="1496525340" endtime="1496525441"><status state="up" reason="arp-response" reason_ttl="0"/>
<address addr="10.11.1.7" addrtype="ipv4"/>
<address addr="00:50:56:89:07:45" addrtype="mac" vendor="VMware"/>
<hostnames>
</hostnames>
<ports><extraports state="open|filtered" count="100">
<extrareasons reason="no-responses" count="100"/>
</extraports>
</ports>
<times srtt="31334" rttvar="31334" to="156670"/>
</host>
<host starttime="1496525340" endtime="1496525454"><status state="up" reason="arp-response" reason_ttl="0"/>
<address addr="10.11.1.8" addrtype="ipv4"/>
<address addr="00:50:56:89:7B:F1" addrtype="mac" vendor="VMware"/>
<hostnames>
</hostnames>
<ports><extraports state="filtered" count="98">
<extrareasons reason="host-prohibiteds" count="98"/>
</extraports>
<port protocol="udp" portid="520"><state state="open|filtered" reason="no-response" reason_ttl="0"/><service name="route" method="table" conf="3"/></port>
<port protocol="udp" portid="631"><state state="open|filtered" reason="no-response" reason_ttl="0"/><service name="ipp" method="table" conf="3"/></port>
</ports>
<times srtt="52243" rttvar="27072" to="160531"/>
</host>
<host starttime="1496525340" endtime="1496525443"><status state="up" reason="arp-response" reason_ttl="0"/>
<address addr="10.11.1.10" addrtype="ipv4"/>
<address addr="00:50:56:89:15:C0" addrtype="mac" vendor="VMware"/>
<hostnames>
</hostnames>
<ports><extraports state="open|filtered" count="100">
<extrareasons reason="no-responses" count="100"/>
</extraports>
</ports>
<times srtt="31312" rttvar="31312" to="156560"/>
</host>
<host starttime="1496525340" endtime="1496525438"><status state="up" reason="arp-response" reason_ttl="0"/>
<address addr="10.11.1.13" addrtype="ipv4"/>
<address addr="00:50:56:89:10:6F" addrtype="mac" vendor="VMware"/>
<hostnames>
</hostnames>
<ports><extraports state="open|filtered" count="100">
<extrareasons reason="no-responses" count="100"/>
</extraports>
</ports>
<times srtt="31954" rttvar="31954" to="159770"/>
</host>
<host starttime="1496525340" endtime="1496525450"><status state="up" reason="arp-response" reason_ttl="0"/>
<address addr="10.11.1.14" addrtype="ipv4"/>
<address addr="00:50:56:89:23:3A" addrtype="mac" vendor="VMware"/>
<hostnames>
</hostnames>
<ports><extraports state="open|filtered" count="100">
<extrareasons reason="no-responses" count="100"/>
</extraports>
</ports>
<times srtt="68546" rttvar="68546" to="342730"/>
</host>
<host starttime="1496525340" endtime="1496525454"><status state="up" reason="arp-response" reason_ttl="0"/>
<address addr="10.11.1.22" addrtype="ipv4"/>
<address addr="00:50:56:89:10:60" addrtype="mac" vendor="VMware"/>
<hostnames>
</hostnames>
<ports><extraports state="closed" count="95">
<extrareasons reason="port-unreaches" count="95"/>
</extraports>
<port protocol="udp" portid="111"><state state="open" reason="udp-response" reason_ttl="64"/><service name="rpcbind" method="table" conf="3"/></port>
<port protocol="udp" portid="137"><state state="open" reason="udp-response" reason_ttl="64"/><service name="netbios-ns" method="table" conf="3"/></port>
<port protocol="udp" portid="138"><state state="open|filtered" reason="no-response" reason_ttl="0"/><service name="netbios-dgm" method="table" conf="3"/></port>
<port protocol="udp" portid="161"><state state="open" reason="udp-response" reason_ttl="64"/><service name="snmp" method="table" conf="3"/></port>
<port protocol="udp" portid="32768"><state state="open|filtered" reason="no-response" reason_ttl="0"/><service name="omad" method="table" conf="3"/></port>
</ports>
<times srtt="40850" rttvar="20886" to="124394"/>
</host>
<host starttime="1496525340" endtime="1496525449"><status state="up" reason="arp-response" reason_ttl="0"/>
<address addr="10.11.1.24" addrtype="ipv4"/>
<address addr="00:50:56:89:2C:E4" addrtype="mac" vendor="VMware"/>
<hostnames>
</hostnames>
<ports><extraports state="closed" count="98">
<extrareasons reason="port-unreaches" count="98"/>
</extraports>
<port protocol="udp" portid="137"><state state="open" reason="udp-response" reason_ttl="64"/><service name="netbios-ns" method="table" conf="3"/></port>
<port protocol="udp" portid="138"><state state="open|filtered" reason="no-response" reason_ttl="0"/><service name="netbios-dgm" method="table" conf="3"/></port>
</ports>
<times srtt="33810" rttvar="7230" to="100000"/>
</host>
<host starttime="1496525340" endtime="1496525446"><status state="up" reason="arp-response" reason_ttl="0"/>
<address addr="10.11.1.31" addrtype="ipv4"/>
<address addr="00:50:56:89:1E:24" addrtype="mac" vendor="VMware"/>
<hostnames>
</hostnames>
<ports><extraports state="closed" count="94">
<extrareasons reason="port-unreaches" count="94"/>
</extraports>
<port protocol="udp" portid="137"><state state="open" reason="udp-response" reason_ttl="128"/><service name="netbios-ns" method="table" conf="3"/></port>
<port protocol="udp" portid="138"><state state="open|filtered" reason="no-response" reason_ttl="0"/><service name="netbios-dgm" method="table" conf="3"/></port>
<port protocol="udp" portid="445"><state state="open|filtered" reason="no-response" reason_ttl="0"/><service name="microsoft-ds" method="table" conf="3"/></port>
<port protocol="udp" portid="500"><state state="open|filtered" reason="no-response" reason_ttl="0"/><service name="isakmp" method="table" conf="3"/></port>
<port protocol="udp" portid="1434"><state state="open|filtered" reason="no-response" reason_ttl="0"/><service name="ms-sql-m" method="table" conf="3"/></port>
<port protocol="udp" portid="4500"><state state="open|filtered" reason="no-response" reason_ttl="0"/><service name="nat-t-ike" method="table" conf="3"/></port>
</ports>
<times srtt="30772" rttvar="1437" to="100000"/>
</host>
<host starttime="1496525340" endtime="1496525464"><status state="up" reason="arp-response" reason_ttl="0"/>
<address addr="10.11.1.35" addrtype="ipv4"/>
<address addr="00:50:56:89:22:01" addrtype="mac" vendor="VMware"/>
<hostnames>
</hostnames>
<ports><extraports state="filtered" count="99">
<extrareasons reason="host-prohibiteds" count="99"/>
</extraports>
<port protocol="udp" portid="631"><state state="open|filtered" reason="no-response" reason_ttl="0"/><service name="ipp" method="table" conf="3"/></port>
</ports>
<times srtt="30920" rttvar="795" to="100000"/>
</host>
<host starttime="1496525340" endtime="1496525453"><status state="up" reason="arp-response" reason_ttl="0"/>
<address addr="10.11.1.39" addrtype="ipv4"/>
<address addr="00:50:56:89:34:51" addrtype="mac" vendor="VMware"/>
<hostnames>
</hostnames>
<ports><extraports state="filtered" count="100">
<extrareasons reason="host-prohibiteds" count="100"/>
</extraports>
</ports>
<times srtt="36494" rttvar="11008" to="100000"/>
</host>
<host starttime="1496525340" endtime="1496525461"><status state="up" reason="arp-response" reason_ttl="0"/>
<address addr="10.11.1.44" addrtype="ipv4"/>
<address addr="00:50:56:89:06:CC" addrtype="mac" vendor="VMware"/>
<hostnames>
</hostnames>
<ports><extraports state="closed" count="100">
<extrareasons reason="port-unreaches" count="100"/>
</extraports>
</ports>
<times srtt="30522" rttvar="819" to="100000"/>
</host>
<host starttime="1496525340" endtime="1496525431"><status state="up" reason="arp-response" reason_ttl="0"/>
<address addr="10.11.1.49" addrtype="ipv4"/>
<address addr="00:50:56:89:72:F8" addrtype="mac" vendor="VMware"/>
<hostnames>
</hostnames>
<ports><extraports state="open|filtered" count="100">
<extrareasons reason="no-responses" count="100"/>
</extraports>
</ports>
<times srtt="29838" rttvar="29838" to="149190"/>
</host>
<host starttime="1496525340" endtime="1496525440"><status state="up" reason="arp-response" reason_ttl="0"/>
<address addr="10.11.1.50" addrtype="ipv4"/>
<address addr="00:50:56:89:35:44" addrtype="mac" vendor="VMware"/>
<hostnames>
</hostnames>
<ports><extraports state="open|filtered" count="100">
<extrareasons reason="no-responses" count="100"/>
</extraports>
</ports>
<times srtt="29752" rttvar="29752" to="148760"/>
</host>
<host starttime="1496525340" endtime="1496525449"><status state="up" reason="arp-response" reason_ttl="0"/>
<address addr="10.11.1.71" addrtype="ipv4"/>
<address addr="00:50:56:89:43:8E" addrtype="mac" vendor="VMware"/>
<hostnames>
</hostnames>
<ports><extraports state="closed" count="100">
<extrareasons reason="port-unreaches" count="100"/>
</extraports>
</ports>
<times srtt="30948" rttvar="2515" to="100000"/>
</host>
<host starttime="1496525340" endtime="1496525444"><status state="up" reason="arp-response" reason_ttl="0"/>
<address addr="10.11.1.72" addrtype="ipv4"/>
<address addr="00:50:56:89:07:B8" addrtype="mac" vendor="VMware"/>
<hostnames>
</hostnames>
<ports><extraports state="closed" count="97">
<extrareasons reason="port-unreaches" count="97"/>
</extraports>
<port protocol="udp" portid="111"><state state="open" reason="udp-response" reason_ttl="64"/><service name="rpcbind" method="table" conf="3"/></port>
<port protocol="udp" portid="2049"><state state="open" reason="udp-response" reason_ttl="64"/><service name="nfs" method="table" conf="3"/></port>
<port protocol="udp" portid="5353"><state state="open" reason="udp-response" reason_ttl="255"/><service name="zeroconf" method="table" conf="3"/></port>
</ports>
<times srtt="32402" rttvar="3210" to="100000"/>
</host>
<host starttime="1496525340" endtime="1496525427"><status state="up" reason="arp-response" reason_ttl="0"/>
<address addr="10.11.1.73" addrtype="ipv4"/>
<address addr="00:50:56:89:6F:F6" addrtype="mac" vendor="VMware"/>
<hostnames>
</hostnames>
<ports><extraports state="open|filtered" count="99">
<extrareasons reason="no-responses" count="99"/>
</extraports>
<port protocol="udp" portid="137"><state state="open" reason="udp-response" reason_ttl="128"/><service name="netbios-ns" method="table" conf="3"/></port>
</ports>
<times srtt="31867" rttvar="2403" to="100000"/>
</host>
<host starttime="1496525340" endtime="1496525441"><status state="up" reason="arp-response" reason_ttl="0"/>
<address addr="10.11.1.115" addrtype="ipv4"/>
<address addr="00:50:56:89:1E:11" addrtype="mac" vendor="VMware"/>
<hostnames>
</hostnames>
<ports><extraports state="closed" count="87">
<extrareasons reason="port-unreaches" count="87"/>
</extraports>
<port protocol="udp" portid="19"><state state="open|filtered" reason="no-response" reason_ttl="0"/><service name="chargen" method="table" conf="3"/></port>
<port protocol="udp" portid="67"><state state="open|filtered" reason="no-response" reason_ttl="0"/><service name="dhcps" method="table" conf="3"/></port>
<port protocol="udp" portid="111"><state state="open" reason="udp-response" reason_ttl="64"/><service name="rpcbind" method="table" conf="3"/></port>
<port protocol="udp" portid="137"><state state="open" reason="udp-response" reason_ttl="64"/><service name="netbios-ns" method="table" conf="3"/></port>
<port protocol="udp" portid="138"><state state="open|filtered" reason="no-response" reason_ttl="0"/><service name="netbios-dgm" method="table" conf="3"/></port>
<port protocol="udp" portid="139"><state state="open|filtered" reason="no-response" reason_ttl="0"/><service name="netbios-ssn" method="table" conf="3"/></port>
<port protocol="udp" portid="161"><state state="open" reason="udp-response" reason_ttl="64"/><service name="snmp" method="table" conf="3"/></port>
<port protocol="udp" portid="177"><state state="open|filtered" reason="no-response" reason_ttl="0"/><service name="xdmcp" method="table" conf="3"/></port>
<port protocol="udp" portid="3456"><state state="open|filtered" reason="no-response" reason_ttl="0"/><service name="IISrpc-or-vat" method="table" conf="3"/></port>
<port protocol="udp" portid="10000"><state state="open|filtered" reason="no-response" reason_ttl="0"/><service name="ndmp" method="table" conf="3"/></port>
<port protocol="udp" portid="31337"><state state="open|filtered" reason="no-response" reason_ttl="0"/><service name="BackOrifice" method="table" conf="3"/></port>
<port protocol="udp" portid="32768"><state state="open|filtered" reason="no-response" reason_ttl="0"/><service name="omad" method="table" conf="3"/></port>
<port protocol="udp" portid="33281"><state state="open|filtered" reason="no-response" reason_ttl="0"/><service name="unknown" method="table" conf="3"/></port>
</ports>
<times srtt="46913" rttvar="17510" to="116953"/>
</host>
<host starttime="1496525340" endtime="1496525344"><status state="up" reason="arp-response" reason_ttl="0"/>
<address addr="10.11.1.116" addrtype="ipv4"/>
<address addr="00:50:56:89:01:33" addrtype="mac" vendor="VMware"/>
<hostnames>
</hostnames>
<ports><extraports state="closed" count="99">
<extrareasons reason="port-unreaches" count="99"/>
</extraports>
<port protocol="udp" portid="514"><state state="open|filtered" reason="no-response" reason_ttl="0"/><service name="syslog" method="table" conf="3"/></port>
</ports>
<times srtt="31550" rttvar="788" to="100000"/>
</host>
<host starttime="1496525340" endtime="1496525448"><status state="up" reason="arp-response" reason_ttl="0"/>
<address addr="10.11.1.125" addrtype="ipv4"/>
<address addr="00:50:56:89:57:9D" addrtype="mac" vendor="VMware"/>
<hostnames>
</hostnames>
<ports><extraports state="open|filtered" count="100">
<extrareasons reason="no-responses" count="100"/>
</extraports>
</ports>
<times srtt="36031" rttvar="36031" to="180155"/>
</host>
<host starttime="1496525340" endtime="1496525429"><status state="up" reason="arp-response" reason_ttl="0"/>
<address addr="10.11.1.128" addrtype="ipv4"/>
<address addr="00:50:56:89:3F:ED" addrtype="mac" vendor="VMware"/>
<hostnames>
</hostnames>
<ports><extraports state="closed" count="92">
<extrareasons reason="port-unreaches" count="92"/>
</extraports>
<port protocol="udp" portid="135"><state state="open|filtered" reason="no-response" reason_ttl="0"/><service name="msrpc" method="table" conf="3"/></port>
<port protocol="udp" portid="137"><state state="open" reason="udp-response" reason_ttl="128"/><service name="netbios-ns" method="table" conf="3"/></port>
<port protocol="udp" portid="138"><state state="open|filtered" reason="no-response" reason_ttl="0"/><service name="netbios-dgm" method="table" conf="3"/></port>
<port protocol="udp" portid="161"><state state="open|filtered" reason="no-response" reason_ttl="0"/><service name="snmp" method="table" conf="3"/></port>
<port protocol="udp" portid="445"><state state="open|filtered" reason="no-response" reason_ttl="0"/><service name="microsoft-ds" method="table" conf="3"/></port>
<port protocol="udp" portid="500"><state state="open|filtered" reason="no-response" reason_ttl="0"/><service name="isakmp" method="table" conf="3"/></port>
<port protocol="udp" portid="1434"><state state="open|filtered" reason="no-response" reason_ttl="0"/><service name="ms-sql-m" method="table" conf="3"/></port>
<port protocol="udp" portid="3456"><state state="open|filtered" reason="no-response" reason_ttl="0"/><service name="IISrpc-or-vat" method="table" conf="3"/></port>
</ports>
<times srtt="33191" rttvar="5346" to="100000"/>
</host>
<host starttime="1496525340" endtime="1496525462"><status state="up" reason="arp-response" reason_ttl="0"/>
<address addr="10.11.1.133" addrtype="ipv4"/>
<address addr="00:50:56:89:34:8C" addrtype="mac" vendor="VMware"/>
<hostnames>
</hostnames>
<ports><extraports state="open|filtered" count="84">
<extrareasons reason="no-responses" count="84"/>
</extraports>
<port protocol="udp" portid="7"><state state="closed" reason="port-unreach" reason_ttl="128"/><service name="echo" method="table" conf="3"/></port>
<port protocol="udp" portid="9"><state state="closed" reason="port-unreach" reason_ttl="128"/><service name="discard" method="table" conf="3"/></port>
<port protocol="udp" portid="53"><state state="closed" reason="port-unreach" reason_ttl="128"/><service name="domain" method="table" conf="3"/></port>
<port protocol="udp" portid="500"><state state="closed" reason="port-unreach" reason_ttl="128"/><service name="isakmp" method="table" conf="3"/></port>
<port protocol="udp" portid="623"><state state="closed" reason="port-unreach" reason_ttl="128"/><service name="asf-rmcp" method="table" conf="3"/></port>
<port protocol="udp" portid="1026"><state state="closed" reason="port-unreach" reason_ttl="128"/><service name="win-rpc" method="table" conf="3"/></port>
<port protocol="udp" portid="1027"><state state="closed" reason="port-unreach" reason_ttl="128"/><service name="unknown" method="table" conf="3"/></port>
<port protocol="udp" portid="1701"><state state="closed" reason="port-unreach" reason_ttl="128"/><service name="L2TP" method="table" conf="3"/></port>
<port protocol="udp" portid="2222"><state state="closed" reason="port-unreach" reason_ttl="128"/><service name="msantipiracy" method="table" conf="3"/></port>
<port protocol="udp" portid="3283"><state state="closed" reason="port-unreach" reason_ttl="128"/><service name="netassistant" method="table" conf="3"/></port>
<port protocol="udp" portid="5060"><state state="closed" reason="port-unreach" reason_ttl="128"/><service name="sip" method="table" conf="3"/></port>
<port protocol="udp" portid="5632"><state state="closed" reason="port-unreach" reason_ttl="128"/><service name="pcanywherestat" method="table" conf="3"/></port>
<port protocol="udp" portid="32768"><state state="closed" reason="port-unreach" reason_ttl="128"/><service name="omad" method="table" conf="3"/></port>
<port protocol="udp" portid="49154"><state state="closed" reason="port-unreach" reason_ttl="128"/><service name="unknown" method="table" conf="3"/></port>
<port protocol="udp" portid="49190"><state state="closed" reason="port-unreach" reason_ttl="128"/><service name="unknown" method="table" conf="3"/></port>
<port protocol="udp" portid="49191"><state state="closed" reason="port-unreach" reason_ttl="128"/><service name="unknown" method="table" conf="3"/></port>
</ports>
<times srtt="31823" rttvar="1109" to="100000"/>
</host>
<host starttime="1496525340" endtime="1496525435"><status state="up" reason="arp-response" reason_ttl="0"/>
<address addr="10.11.1.136" addrtype="ipv4"/>
<address addr="00:50:56:89:19:1D" addrtype="mac" vendor="VMware"/>
<hostnames>
</hostnames>
<ports><extraports state="closed" count="89">
<extrareasons reason="port-unreaches" count="89"/>
</extraports>
<port protocol="udp" portid="49"><state state="open|filtered" reason="no-response" reason_ttl="0"/><service name="tacacs" method="table" conf="3"/></port>
<port protocol="udp" portid="69"><state state="open|filtered" reason="no-response" reason_ttl="0"/><service name="tftp" method="table" conf="3"/></port>
<port protocol="udp" portid="111"><state state="open|filtered" reason="no-response" reason_ttl="0"/><service name="rpcbind" method="table" conf="3"/></port>
<port protocol="udp" portid="136"><state state="open|filtered" reason="no-response" reason_ttl="0"/><service name="profile" method="table" conf="3"/></port>
<port protocol="udp" portid="137"><state state="open" reason="udp-response" reason_ttl="64"/><service name="netbios-ns" method="table" conf="3"/></port>
<port protocol="udp" portid="138"><state state="open|filtered" reason="no-response" reason_ttl="0"/><service name="netbios-dgm" method="table" conf="3"/></port>
<port protocol="udp" portid="497"><state state="open|filtered" reason="no-response" reason_ttl="0"/><service name="retrospect" method="table" conf="3"/></port>
<port protocol="udp" portid="1718"><state state="open|filtered" reason="no-response" reason_ttl="0"/><service name="h225gatedisc" method="table" conf="3"/></port>
<port protocol="udp" portid="1812"><state state="open|filtered" reason="no-response" reason_ttl="0"/><service name="radius" method="table" conf="3"/></port>
<port protocol="udp" portid="10000"><state state="open|filtered" reason="no-response" reason_ttl="0"/><service name="ndmp" method="table" conf="3"/></port>
<port protocol="udp" portid="17185"><state state="open|filtered" reason="no-response" reason_ttl="0"/><service name="wdbrpc" method="table" conf="3"/></port>
</ports>
<times srtt="48007" rttvar="34024" to="184103"/>
</host>
<host starttime="1496525340" endtime="1496525436"><status state="up" reason="arp-response" reason_ttl="0"/>
<address addr="10.11.1.141" addrtype="ipv4"/>
<address addr="00:50:56:89:5C:42" addrtype="mac" vendor="VMware"/>
<hostnames>
</hostnames>
<ports><extraports state="open|filtered" count="100">
<extrareasons reason="no-responses" count="100"/>
</extraports>
</ports>
<times srtt="32376" rttvar="32376" to="161880"/>
</host>
<host starttime="1496525340" endtime="1496525449"><status state="up" reason="arp-response" reason_ttl="0"/>
<address addr="10.11.1.145" addrtype="ipv4"/>
<address addr="00:50:56:89:6E:4B" addrtype="mac" vendor="VMware"/>
<hostnames>
</hostnames>
<ports><extraports state="open|filtered" count="99">
<extrareasons reason="no-responses" count="99"/>
</extraports>
<port protocol="udp" portid="137"><state state="open" reason="udp-response" reason_ttl="128"/><service name="netbios-ns" method="table" conf="3"/></port>
</ports>
<times srtt="31995" rttvar="3616" to="100000"/>
</host>
<host starttime="1496525340" endtime="1496525449"><status state="up" reason="arp-response" reason_ttl="0"/>
<address addr="10.11.1.146" addrtype="ipv4"/>
<address addr="00:50:56:89:31:60" addrtype="mac" vendor="VMware"/>
<hostnames>
</hostnames>
<ports><extraports state="closed" count="100">
<extrareasons reason="port-unreaches" count="100"/>
</extraports>
</ports>
<times srtt="31741" rttvar="3888" to="100000"/>
</host>
<host starttime="1496525340" endtime="1496525427"><status state="up" reason="arp-response" reason_ttl="0"/>
<address addr="10.11.1.202" addrtype="ipv4"/>
<address addr="00:50:56:89:01:54" addrtype="mac" vendor="VMware"/>
<hostnames>
</hostnames>
<ports><extraports state="closed" count="95">
<extrareasons reason="port-unreaches" count="95"/>
</extraports>
<port protocol="udp" portid="137"><state state="open" reason="udp-response" reason_ttl="128"/><service name="netbios-ns" method="table" conf="3"/></port>
<port protocol="udp" portid="138"><state state="open|filtered" reason="no-response" reason_ttl="0"/><service name="netbios-dgm" method="table" conf="3"/></port>
<port protocol="udp" portid="445"><state state="open|filtered" reason="no-response" reason_ttl="0"/><service name="microsoft-ds" method="table" conf="3"/></port>
<port protocol="udp" portid="500"><state state="open|filtered" reason="no-response" reason_ttl="0"/><service name="isakmp" method="table" conf="3"/></port>
<port protocol="udp" portid="3456"><state state="open|filtered" reason="no-response" reason_ttl="0"/><service name="IISrpc-or-vat" method="table" conf="3"/></port>
</ports>
<times srtt="37199" rttvar="13746" to="100000"/>
</host>
<host starttime="1496525340" endtime="1496525428"><status state="up" reason="arp-response" reason_ttl="0"/>
<address addr="10.11.1.209" addrtype="ipv4"/>
<address addr="00:50:56:89:47:8F" addrtype="mac" vendor="VMware"/>
<hostnames>
</hostnames>
<ports><extraports state="closed" count="97">
<extrareasons reason="port-unreaches" count="97"/>
</extraports>
<port protocol="udp" portid="111"><state state="open" reason="udp-response" reason_ttl="255"/><service name="rpcbind" method="table" conf="3"/></port>
<port protocol="udp" portid="520"><state state="open" reason="udp-response" reason_ttl="255"/><service name="route" method="table" conf="3"/></port>
<port protocol="udp" portid="32771"><state state="open|filtered" reason="no-response" reason_ttl="0"/><service name="sometimes-rpc6" method="table" conf="3"/></port>
</ports>
<times srtt="32559" rttvar="3129" to="100000"/>
</host>
<host starttime="1496525340" endtime="1496525447"><status state="up" reason="arp-response" reason_ttl="0"/>
<address addr="10.11.1.217" addrtype="ipv4"/>
<address addr="00:50:56:89:79:13" addrtype="mac" vendor="VMware"/>
<hostnames>
</hostnames>
<ports><extraports state="closed" count="93">
<extrareasons reason="port-unreaches" count="93"/>
</extraports>
<port protocol="udp" portid="69"><state state="open|filtered" reason="no-response" reason_ttl="0"/><service name="tftp" method="table" conf="3"/></port>
<port protocol="udp" portid="111"><state state="open" reason="udp-response" reason_ttl="64"/><service name="rpcbind" method="table" conf="3"/></port>
<port protocol="udp" portid="123"><state state="open" reason="udp-response" reason_ttl="64"/><service name="ntp" method="table" conf="3"/></port>
<port protocol="udp" portid="1646"><state state="open|filtered" reason="no-response" reason_ttl="0"/><service name="radacct" method="table" conf="3"/></port>
<port protocol="udp" portid="5000"><state state="open|filtered" reason="no-response" reason_ttl="0"/><service name="upnp" method="table" conf="3"/></port>
<port protocol="udp" portid="5060"><state state="open|filtered" reason="no-response" reason_ttl="0"/><service name="sip" method="table" conf="3"/></port>
<port protocol="udp" portid="49182"><state state="open|filtered" reason="no-response" reason_ttl="0"/><service name="unknown" method="table" conf="3"/></port>
</ports>
<times srtt="30377" rttvar="1550" to="100000"/>
</host>
<host starttime="1496525340" endtime="1496525442"><status state="up" reason="arp-response" reason_ttl="0"/>
<address addr="10.11.1.218" addrtype="ipv4"/>
<address addr="00:50:56:89:67:AB" addrtype="mac" vendor="VMware"/>
<hostnames>
</hostnames>
<ports><extraports state="open|filtered" count="99">
<extrareasons reason="no-responses" count="99"/>
</extraports>
<port protocol="udp" portid="137"><state state="open" reason="udp-response" reason_ttl="128"/><service name="netbios-ns" method="table" conf="3"/></port>
</ports>
<times srtt="31905" rttvar="1943" to="100000"/>
</host>
<host starttime="1496525340" endtime="1496525446"><status state="up" reason="arp-response" reason_ttl="0"/>
<address addr="10.11.1.219" addrtype="ipv4"/>
<address addr="00:50:56:89:7A:36" addrtype="mac" vendor="VMware"/>
<hostnames>
</hostnames>
<ports><extraports state="open|filtered" count="100">
<extrareasons reason="no-responses" count="100"/>
</extraports>
</ports>
<times srtt="31223" rttvar="31223" to="156115"/>
</host>
<host starttime="1496525340" endtime="1496525491"><status state="up" reason="arp-response" reason_ttl="0"/>
<address addr="10.11.1.220" addrtype="ipv4"/>
<address addr="00:50:56:89:05:74" addrtype="mac" vendor="VMware"/>
<hostnames>
</hostnames>
<ports><extraports state="closed" count="93">
<extrareasons reason="port-unreaches" count="93"/>
</extraports>
<port protocol="udp" portid="53"><state state="open" reason="udp-response" reason_ttl="128"/><service name="domain" method="table" conf="3"/></port>
<port protocol="udp" portid="88"><state state="open|filtered" reason="no-response" reason_ttl="0"/><service name="kerberos-sec" method="table" conf="3"/></port>
<port protocol="udp" portid="137"><state state="open" reason="udp-response" reason_ttl="128"/><service name="netbios-ns" method="table" conf="3"/></port>
<port protocol="udp" portid="138"><state state="open|filtered" reason="no-response" reason_ttl="0"/><service name="netbios-dgm" method="table" conf="3"/></port>
<port protocol="udp" portid="500"><state state="open|filtered" reason="no-response" reason_ttl="0"/><service name="isakmp" method="table" conf="3"/></port>
<port protocol="udp" portid="4500"><state state="open|filtered" reason="no-response" reason_ttl="0"/><service name="nat-t-ike" method="table" conf="3"/></port>
<port protocol="udp" portid="49190"><state state="open|filtered" reason="no-response" reason_ttl="0"/><service name="unknown" method="table" conf="3"/></port>
</ports>
<times srtt="35571" rttvar="8588" to="100000"/>
</host>
<host starttime="1496525340" endtime="1496525446"><status state="up" reason="arp-response" reason_ttl="0"/>
<address addr="10.11.1.221" addrtype="ipv4"/>
<address addr="00:50:56:89:58:65" addrtype="mac" vendor="VMware"/>
<hostnames>
</hostnames>
<ports><extraports state="open|filtered" count="98">
<extrareasons reason="no-responses" count="98"/>
</extraports>
<port protocol="udp" portid="53"><state state="open" reason="udp-response" reason_ttl="128"/><service name="domain" method="table" conf="3"/></port>
<port protocol="udp" portid="137"><state state="open" reason="udp-response" reason_ttl="128"/><service name="netbios-ns" method="table" conf="3"/></port>
</ports>
<times srtt="31664" rttvar="14224" to="100000"/>
</host>
<host starttime="1496525340" endtime="1496525491"><status state="up" reason="arp-response" reason_ttl="0"/>
<address addr="10.11.1.223" addrtype="ipv4"/>
<address addr="00:50:56:89:3E:DA" addrtype="mac" vendor="VMware"/>
<hostnames>
</hostnames>
<ports><extraports state="closed" count="94">
<extrareasons reason="port-unreaches" count="94"/>
</extraports>
<port protocol="udp" portid="53"><state state="open|filtered" reason="no-response" reason_ttl="0"/><service name="domain" method="table" conf="3"/></port>
<port protocol="udp" portid="137"><state state="open" reason="udp-response" reason_ttl="128"/><service name="netbios-ns" method="table" conf="3"/></port>
<port protocol="udp" portid="138"><state state="open|filtered" reason="no-response" reason_ttl="0"/><service name="netbios-dgm" method="table" conf="3"/></port>
<port protocol="udp" portid="500"><state state="open|filtered" reason="no-response" reason_ttl="0"/><service name="isakmp" method="table" conf="3"/></port>
<port protocol="udp" portid="1701"><state state="open|filtered" reason="no-response" reason_ttl="0"/><service name="L2TP" method="table" conf="3"/></port>
<port protocol="udp" portid="4500"><state state="open|filtered" reason="no-response" reason_ttl="0"/><service name="nat-t-ike" method="table" conf="3"/></port>
</ports>
<times srtt="31154" rttvar="853" to="100000"/>
</host>
<host starttime="1496525340" endtime="1496525432"><status state="up" reason="arp-response" reason_ttl="0"/>
<address addr="10.11.1.226" addrtype="ipv4"/>
<address addr="00:50:56:89:7B:69" addrtype="mac" vendor="VMware"/>
<hostnames>
</hostnames>
<ports><extraports state="open|filtered" count="100">
<extrareasons reason="no-responses" count="100"/>
</extraports>
</ports>
<times srtt="39771" rttvar="39771" to="198855"/>
</host>
<host starttime="1496525340" endtime="1496525431"><status state="up" reason="arp-response" reason_ttl="0"/>
<address addr="10.11.1.227" addrtype="ipv4"/>
<address addr="00:50:56:89:71:CB" addrtype="mac" vendor="VMware"/>
<hostnames>
</hostnames>
<ports><extraports state="closed" count="91">
<extrareasons reason="port-unreaches" count="91"/>
</extraports>
<port protocol="udp" portid="135"><state state="open|filtered" reason="no-response" reason_ttl="0"/><service name="msrpc" method="table" conf="3"/></port>
<port protocol="udp" portid="137"><state state="open" reason="udp-response" reason_ttl="128"/><service name="netbios-ns" method="table" conf="3"/></port>
<port protocol="udp" portid="138"><state state="open|filtered" reason="no-response" reason_ttl="0"/><service name="netbios-dgm" method="table" conf="3"/></port>
<port protocol="udp" portid="161"><state state="open|filtered" reason="no-response" reason_ttl="0"/><service name="snmp" method="table" conf="3"/></port>
<port protocol="udp" portid="445"><state state="open|filtered" reason="no-response" reason_ttl="0"/><service name="microsoft-ds" method="table" conf="3"/></port>
<port protocol="udp" portid="500"><state state="open|filtered" reason="no-response" reason_ttl="0"/><service name="isakmp" method="table" conf="3"/></port>
<port protocol="udp" portid="1030"><state state="open|filtered" reason="no-response" reason_ttl="0"/><service name="iad1" method="table" conf="3"/></port>
<port protocol="udp" portid="1434"><state state="open|filtered" reason="no-response" reason_ttl="0"/><service name="ms-sql-m" method="table" conf="3"/></port>
<port protocol="udp" portid="3456"><state state="open|filtered" reason="no-response" reason_ttl="0"/><service name="IISrpc-or-vat" method="table" conf="3"/></port>
</ports>
<times srtt="30866" rttvar="1565" to="100000"/>
</host>
<host starttime="1496525340" endtime="1496525449"><status state="up" reason="arp-response" reason_ttl="0"/>
<address addr="10.11.1.229" addrtype="ipv4"/>
<address addr="00:50:56:89:75:CF" addrtype="mac" vendor="VMware"/>
<hostnames>
</hostnames>
<ports><extraports state="open|filtered" count="98">
<extrareasons reason="no-responses" count="98"/>
</extraports>
<port protocol="udp" portid="137"><state state="open" reason="udp-response" reason_ttl="128"/><service name="netbios-ns" method="table" conf="3"/></port>
<port protocol="udp" portid="1900"><state state="closed" reason="port-unreach" reason_ttl="128"/><service name="upnp" method="table" conf="3"/></port>
</ports>
<times srtt="31538" rttvar="2442" to="100000"/>
</host>
<host starttime="1496525340" endtime="1496525490"><status state="up" reason="arp-response" reason_ttl="0"/>
<address addr="10.11.1.230" addrtype="ipv4"/>
<address addr="00:50:56:89:3A:1C" addrtype="mac" vendor="VMware"/>
<hostnames>
</hostnames>
<ports><extraports state="closed" count="93">
<extrareasons reason="port-unreaches" count="93"/>
</extraports>
<port protocol="udp" portid="80"><state state="open|filtered" reason="no-response" reason_ttl="0"/><service name="http" method="table" conf="3"/></port>
<port protocol="udp" portid="137"><state state="open" reason="udp-response" reason_ttl="128"/><service name="netbios-ns" method="table" conf="3"/></port>
<port protocol="udp" portid="138"><state state="open|filtered" reason="no-response" reason_ttl="0"/><service name="netbios-dgm" method="table" conf="3"/></port>
<port protocol="udp" portid="500"><state state="open|filtered" reason="no-response" reason_ttl="0"/><service name="isakmp" method="table" conf="3"/></port>
<port protocol="udp" portid="1025"><state state="open|filtered" reason="no-response" reason_ttl="0"/><service name="blackjack" method="table" conf="3"/></port>
<port protocol="udp" portid="1701"><state state="open|filtered" reason="no-response" reason_ttl="0"/><service name="L2TP" method="table" conf="3"/></port>
<port protocol="udp" portid="4500"><state state="open|filtered" reason="no-response" reason_ttl="0"/><service name="nat-t-ike" method="table" conf="3"/></port>
</ports>
<times srtt="139039" rttvar="184360" to="876479"/>
</host>
<host starttime="1496525340" endtime="1496525447"><status state="up" reason="arp-response" reason_ttl="0"/>
<address addr="10.11.1.234" addrtype="ipv4"/>
<address addr="00:50:56:89:3F:2D" addrtype="mac" vendor="VMware"/>
<hostnames>
</hostnames>
<ports><extraports state="closed" count="90">
<extrareasons reason="port-unreaches" count="90"/>
</extraports>
<port protocol="udp" portid="68"><state state="open|filtered" reason="no-response" reason_ttl="0"/><service name="dhcpc" method="table" conf="3"/></port>
<port protocol="udp" portid="136"><state state="open|filtered" reason="no-response" reason_ttl="0"/><service name="profile" method="table" conf="3"/></port>
<port protocol="udp" portid="997"><state state="open|filtered" reason="no-response" reason_ttl="0"/><service name="maitrd" method="table" conf="3"/></port>
<port protocol="udp" portid="1434"><state state="open|filtered" reason="no-response" reason_ttl="0"/><service name="ms-sql-m" method="table" conf="3"/></port>
<port protocol="udp" portid="1718"><state state="open|filtered" reason="no-response" reason_ttl="0"/><service name="h225gatedisc" method="table" conf="3"/></port>
<port protocol="udp" portid="1812"><state state="open|filtered" reason="no-response" reason_ttl="0"/><service name="radius" method="table" conf="3"/></port>
<port protocol="udp" portid="10000"><state state="open|filtered" reason="no-response" reason_ttl="0"/><service name="ndmp" method="table" conf="3"/></port>
<port protocol="udp" portid="17185"><state state="open|filtered" reason="no-response" reason_ttl="0"/><service name="wdbrpc" method="table" conf="3"/></port>
<port protocol="udp" portid="32768"><state state="open|filtered" reason="no-response" reason_ttl="0"/><service name="omad" method="table" conf="3"/></port>
<port protocol="udp" portid="49192"><state state="open|filtered" reason="no-response" reason_ttl="0"/><service name="unknown" method="table" conf="3"/></port>
</ports>
<times srtt="60643" rttvar="17611" to="131087"/>
</host>
<host starttime="1496525340" endtime="1496525453"><status state="up" reason="arp-response" reason_ttl="0"/>
<address addr="10.11.1.237" addrtype="ipv4"/>
<address addr="00:50:56:89:2C:47" addrtype="mac" vendor="VMware"/>
<hostnames>
</hostnames>
<ports><extraports state="closed" count="96">
<extrareasons reason="port-unreaches" count="96"/>
</extraports>
<port protocol="udp" portid="111"><state state="open" reason="udp-response" reason_ttl="64"/><service name="rpcbind" method="table" conf="3"/></port>
<port protocol="udp" portid="623"><state state="open|filtered" reason="no-response" reason_ttl="0"/><service name="asf-rmcp" method="table" conf="3"/></port>
<port protocol="udp" portid="1900"><state state="open|filtered" reason="no-response" reason_ttl="0"/><service name="upnp" method="table" conf="3"/></port>
<port protocol="udp" portid="5353"><state state="open" reason="udp-response" reason_ttl="255"/><service name="zeroconf" method="table" conf="3"/></port>
</ports>
<times srtt="33600" rttvar="5833" to="100000"/>
</host>
<host starttime="1496525340" endtime="1496525451"><status state="up" reason="arp-response" reason_ttl="0"/>
<address addr="10.11.1.238" addrtype="ipv4"/>
<address addr="00:50:56:89:10:92" addrtype="mac" vendor="VMware"/>
<hostnames>
</hostnames>
<ports><extraports state="closed" count="92">
<extrareasons reason="port-unreaches" count="92"/>
</extraports>
<port protocol="udp" portid="111"><state state="open" reason="udp-response" reason_ttl="64"/><service name="rpcbind" method="table" conf="3"/></port>
<port protocol="udp" portid="997"><state state="open|filtered" reason="no-response" reason_ttl="0"/><service name="maitrd" method="table" conf="3"/></port>
<port protocol="udp" portid="1718"><state state="open|filtered" reason="no-response" reason_ttl="0"/><service name="h225gatedisc" method="table" conf="3"/></port>
<port protocol="udp" portid="1900"><state state="open|filtered" reason="no-response" reason_ttl="0"/><service name="upnp" method="table" conf="3"/></port>
<port protocol="udp" portid="5353"><state state="open" reason="udp-response" reason_ttl="255"/><service name="zeroconf" method="table" conf="3"/></port>
<port protocol="udp" portid="10000"><state state="open|filtered" reason="no-response" reason_ttl="0"/><service name="ndmp" method="table" conf="3"/></port>
<port protocol="udp" portid="17185"><state state="open|filtered" reason="no-response" reason_ttl="0"/><service name="wdbrpc" method="table" conf="3"/></port>
<port protocol="udp" portid="49153"><state state="open|filtered" reason="no-response" reason_ttl="0"/><service name="unknown" method="table" conf="3"/></port>
</ports>
<times srtt="47172" rttvar="32291" to="176336"/>
</host>
<host starttime="1496525340" endtime="1496525414"><status state="up" reason="arp-response" reason_ttl="0"/>
<address addr="10.11.1.247" addrtype="ipv4"/>
<address addr="00:50:56:89:19:0D" addrtype="mac" vendor="VMware"/>
<hostnames>
</hostnames>
<ports><extraports state="closed" count="94">
<extrareasons reason="port-unreaches" count="94"/>
</extraports>
<port protocol="udp" portid="137"><state state="open" reason="udp-response" reason_ttl="128"/><service name="netbios-ns" method="table" conf="3"/></port>
<port protocol="udp" portid="138"><state state="open|filtered" reason="no-response" reason_ttl="0"/><service name="netbios-dgm" method="table" conf="3"/></port>
<port protocol="udp" portid="445"><state state="open|filtered" reason="no-response" reason_ttl="0"/><service name="microsoft-ds" method="table" conf="3"/></port>
<port protocol="udp" portid="500"><state state="open|filtered" reason="no-response" reason_ttl="0"/><service name="isakmp" method="table" conf="3"/></port>
<port protocol="udp" portid="1900"><state state="open|filtered" reason="no-response" reason_ttl="0"/><service name="upnp" method="table" conf="3"/></port>
<port protocol="udp" portid="4500"><state state="open|filtered" reason="no-response" reason_ttl="0"/><service name="nat-t-ike" method="table" conf="3"/></port>
</ports>
<times srtt="30430" rttvar="1075" to="100000"/>
</host>
<host starttime="1496525340" endtime="1496525450"><status state="up" reason="arp-response" reason_ttl="0"/>
<address addr="10.11.1.251" addrtype="ipv4"/>
<address addr="00:50:56:89:61:87" addrtype="mac" vendor="VMware"/>
<hostnames>
</hostnames>
<ports><extraports state="open|filtered" count="100">
<extrareasons reason="no-responses" count="100"/>
</extraports>
</ports>
<times srtt="31603" rttvar="31603" to="158015"/>
</host>
<host starttime="1496525340" endtime="1496525451"><status state="up" reason="arp-response" reason_ttl="0"/>
<address addr="10.11.1.252" addrtype="ipv4"/>
<address addr="00:50:56:89:5A:02" addrtype="mac" vendor="VMware"/>
<hostnames>
</hostnames>
<ports><extraports state="open|filtered" count="100">
<extrareasons reason="no-responses" count="100"/>
</extraports>
</ports>
<times srtt="32433" rttvar="32433" to="162165"/>
</host>
<runstats><finished time="1496525492" timestr="Sat Jun  3 17:31:32 2017" elapsed="151.54" summary="Nmap done at Sat Jun  3 17:31:32 2017; 256 IP addresses (44 hosts up) scanned in 151.54 seconds" exit="success"/><hosts up="44" down="212" total="256"/>
</runstats>
</nmaprun>
